{
  "Packaging|Method|Well Packed": [
    "ATTR_20",
    "ATTR_184",
    "ATTR_301",
    "ATTR_185"
  ],
  "Packaging|Method|Dispenser Box": [
    "ATTR_30",
    "ATTR_211",
    "ATTR_340"
  ],
  "Packaging|Method|Spool": [
    "ATTR_316",
    "ATTR_338",
    "ATTR_460"
  ],
  "Packaging|Method|Plastic Bag": [
    "ATTR_280",
    "ATTR_339"
  ],
  "Packaging|Method|Individual Pieces": [
    "ATTR_452"
  ],
  "Packaging|Condition|Poor Internal": [
    "ATTR_130"
  ],
  "Packaging|Condition|Tangled": [
    "ATTR_391"
  ],
  "Packaging|Condition|Torn and Damp": [
    "ATTR_453"
  ],
  "Packaging|Labeling|Lack of": [
    "ATTR_129"
  ],
  "Packaging|Labeling|Stamped Lettering": [
    "ATTR_365"
  ],
  "Packaging|Labeling|Size and Length Markings": [
    "ATTR_317"
  ],
  "Packaging|Presentation|Not on Spool": [
    "ATTR_390"
  ],
  "Packaging|Presentation|Tightly Wrapped": [
    "ATTR_70",
    "ATTR_467"
  ],
  "Packaging|Presentation|Zip Tied": [
    "ATTR_71"
  ],
  "Packaging|Presentation|Not Folded": [
    "ATTR_218",
    "ATTR_219"
  ],
  "Packaging|Presentation|Poorly Packaged": [
    "ATTR_272"
  ],
  "Packaging|Presentation|Crimped Bundled": [
    "ATTR_423"
  ],
  "Dimensions|Length|Accuracy": [
    "ATTR_68"
  ],
  "Dimensions|Accuracy|Accurate": [
    "ATTR_120",
    "ATTR_395",
    "ATTR_127",
    "ATTR_312",
    "ATTR_321",
    "ATTR_13",
    "ATTR_294",
    "ATTR_384",
    "ATTR_125",
    "ATTR_181",
    "ATTR_248",
    "ATTR_503",
    "ATTR_189",
    "ATTR_394",
    "perf_41"
  ],
  "Dimensions|Length|Short": [
    "ATTR_168",
    "ATTR_275",
    "ATTR_278",
    "ATTR_67",
    "ATTR_276",
    "ATTR_306"
  ],
  "Dimensions|Length|Specific Length": [
    "ATTR_215",
    "ATTR_27",
    "ATTR_268",
    "ATTR_137",
    "ATTR_12",
    "ATTR_156",
    "ATTR_267",
    "ATTR_474",
    "ATTR_376",
    "ATTR_413",
    "ATTR_475",
    "ATTR_11",
    "ATTR_187",
    "ATTR_55",
    "ATTR_85",
    "ATTR_355",
    "ATTR_86",
    "ATTR_277"
  ],
  "Dimensions|Size|Small": [
    "ATTR_333",
    "ATTR_15",
    "ATTR_327",
    "ATTR_164",
    "ATTR_235",
    "ATTR_401",
    "ATTR_484"
  ],
  "Dimensions|Length|Long": [
    "ATTR_89",
    "ATTR_56",
    "ATTR_172",
    "ATTR_274",
    "ATTR_19",
    "ATTR_36"
  ],
  "Dimensions|Size|Specific": [
    "ATTR_257",
    "ATTR_440"
  ],
  "Dimensions|Wall Thickness|Thin": [
    "ATTR_83",
    "ATTR_167",
    "ATTR_229",
    "ATTR_242",
    "ATTR_266",
    "ATTR_23",
    "ATTR_281",
    "ATTR_454",
    "ATTR_65",
    "ATTR_324",
    "ATTR_363",
    "ATTR_200"
  ],
  "Dimensions|Wall Thickness|Specific Measurement": [
    "ATTR_106",
    "ATTR_362",
    "ATTR_107",
    "ATTR_421",
    "ATTR_337",
    "ATTR_422",
    "ATTR_495",
    "ATTR_497",
    "ATTR_498",
    "ATTR_499"
  ],
  "Dimensions|Wall Thickness|Thick": [
    "ATTR_114",
    "ATTR_143",
    "ATTR_260",
    "ATTR_226",
    "ATTR_295",
    "ATTR_320",
    "ATTR_112",
    "ATTR_57",
    "ATTR_381",
    "ATTR_419",
    "ATTR_220",
    "ATTR_325",
    "ATTR_234",
    "ATTR_103",
    "ATTR_243",
    "ATTR_416",
    "ATTR_179",
    "ATTR_159",
    "ATTR_450",
    "ATTR_282",
    "ATTR_134",
    "ATTR_32",
    "ATTR_66",
    "ATTR_180"
  ],
  "Dimensions|Diameter|Specific Size": [
    "ATTR_176",
    "ATTR_210"
  ],
  "Compatibility:Specific Equipment Fit": [
    "ATTR_357",
    "ATTR_358",
    "ATTR_359",
    "ATTR_369",
    "ATTR_370",
    "ATTR_373",
    "ATTR_162",
    "ATTR_163"
  ],
  "Dimensions|Diameter|General": [
    "ATTR_400"
  ],
  "Dimensions|Diameter|Inner|Measurement": [
    "ATTR_0",
    "ATTR_5",
    "ATTR_6",
    "ATTR_38",
    "ATTR_39",
    "ATTR_42",
    "ATTR_43",
    "ATTR_47",
    "ATTR_142",
    "ATTR_404",
    "ATTR_155",
    "ATTR_165",
    "ATTR_166",
    "ATTR_310",
    "ATTR_313",
    "ATTR_174",
    "ATTR_175",
    "ATTR_201",
    "ATTR_258",
    "ATTR_265",
    "ATTR_364",
    "ATTR_490",
    "ATTR_492",
    "ATTR_496"
  ],
  "Dimensions|Diameter|Outer|Measurement": [
    "ATTR_3",
    "ATTR_356",
    "ATTR_361",
    "ATTR_489",
    "ATTR_26",
    "ATTR_44",
    "ATTR_46",
    "ATTR_48",
    "ATTR_80",
    "ATTR_81",
    "ATTR_40",
    "ATTR_41",
    "ATTR_45",
    "ATTR_491",
    "ATTR_76",
    "ATTR_113",
    "ATTR_136",
    "ATTR_173",
    "ATTR_292",
    "ATTR_105",
    "ATTR_213",
    "ATTR_342",
    "ATTR_411",
    "ATTR_412",
    "ATTR_332",
    "ATTR_473",
    "ATTR_1",
    "ATTR_2",
    "ATTR_4",
    "ATTR_7",
    "ATTR_225",
    "ATTR_389",
    "ATTR_259",
    "ATTR_293",
    "ATTR_360",
    "ATTR_449",
    "ATTR_493",
    "ATTR_494"
  ],
  "Dimensions|Diameter|Inner|Comparison": [
    "ATTR_230",
    "ATTR_368"
  ],
  "Dimensions|Diameter|Outer|Specific Fit": [
    "ATTR_371",
    "ATTR_374",
    "ATTR_8"
  ],
  "Dimensions|Diameter|Outer|Comparison": [
    "ATTR_309"
  ],
  "Dimensions|Size|Specifications": [
    "ATTR_304"
  ],
  "Dimensions|Size|Availability": [
    "ATTR_212"
  ],
  "Dimensions|General Measurement": [
    "ATTR_82",
    "ATTR_88",
    "ATTR_104",
    "ATTR_121",
    "ATTR_231",
    "ATTR_407",
    "ATTR_448",
    "ATTR_483"
  ],
  "Dimensions|Comparison": [
    "ATTR_305"
  ],
  "Dimensions|Accuracy|Inaccurate": [
    "ATTR_14",
    "ATTR_151",
    "ATTR_509",
    "ATTR_311",
    "ATTR_322",
    "ATTR_469"
  ],
  "Value:Price|Expensive": [
    "ATTR_308"
  ],
  "Value:Price|Low": [
    "ATTR_366"
  ],
  "Value:Price|General": [
    "ATTR_153",
    "ATTR_154"
  ],
  "Transparency|Clear": [
    "ATTR_50",
    "ATTR_91",
    "ATTR_470",
    "ATTR_236",
    "ATTR_145",
    "ATTR_29",
    "ATTR_177",
    "ATTR_108",
    "ATTR_52",
    "ATTR_351",
    "ATTR_481",
    "ATTR_444"
  ],
  "Transparency|Translucent": [
    "ATTR_296",
    "ATTR_287",
    "ATTR_506",
    "ATTR_93",
    "ATTR_207",
    "ATTR_415",
    "ATTR_97",
    "ATTR_314"
  ],
  "Color|White": [
    "ATTR_109",
    "ATTR_447",
    "ATTR_94",
    "ATTR_17",
    "ATTR_217",
    "ATTR_350",
    "ATTR_205"
  ],
  "Transparency|Opaque": [
    "ATTR_25",
    "ATTR_204",
    "ATTR_346"
  ],
  "Transparency|Not Clear": [
    "ATTR_96",
    "ATTR_203",
    "ATTR_500"
  ],
  "Color|Discolored": [
    "ATTR_110",
    "ATTR_323"
  ],
  "Internal Structure:Deformity": [
    "ATTR_511"
  ],
  "Markings|Print": [
    "ATTR_256"
  ],
  "Markings|Printed Lettering": [
    "ATTR_206"
  ],
  "Performance|Workability": [
    "ATTR_161",
    "ATTR_190"
  ],
  "Shape|Cross Section:Physical Characteristics": [
    "ATTR_438",
    "ATTR_61",
    "ATTR_84",
    "ATTR_63"
  ],
  "Shape|Overall Form:Physical Characteristics": [
    "ATTR_18",
    "ATTR_62",
    "ATTR_195",
    "ATTR_315",
    "ATTR_476",
    "ATTR_60",
    "ATTR_329",
    "ATTR_380",
    "ATTR_399"
  ],
  "Shape|Shape Retention:Physical Characteristics": [
    "ATTR_102",
    "ATTR_443",
    "ATTR_459",
    "ATTR_428",
    "ATTR_223"
  ],
  "Storage|Not Long Term": [
    "ATTR_123"
  ],
  "Material|Structure|Reinforcement": [
    "ATTR_251",
    "ATTR_193",
    "ATTR_178",
    "ATTR_117"
  ],
  "Material|Structure|Thickness": [
    "ATTR_214",
    "ATTR_426"
  ],
  "Material|Properties|Clarity": [
    "ATTR_9",
    "ATTR_132",
    "ATTR_240",
    "ATTR_336"
  ],
  "Material|Composition|Plastic": [
    "ATTR_269",
    "ATTR_64",
    "ATTR_75",
    "ATTR_385",
    "ATTR_462"
  ],
  "Color|Blue Tinted": [
    "ATTR_482"
  ],
  "Surface Condition|Texture:Material Properties": [
    "ATTR_118",
    "ATTR_318",
    "ATTR_116",
    "ATTR_429",
    "ATTR_430",
    "ATTR_456",
    "ATTR_21",
    "ATTR_22",
    "ATTR_479",
    "ATTR_434"
  ],
  "Product Accuracy:Description Match": [
    "ATTR_504",
    "ATTR_208",
    "ATTR_169"
  ],
  "Material|Composition|Purity": [
    "ATTR_241"
  ],
  "Material|Composition|Rubber-like": [
    "ATTR_199",
    "ATTR_139",
    "ATTR_386",
    "ATTR_463"
  ],
  "Material|Properties|Flexibility": [
    "ATTR_191",
    "ATTR_150",
    "ATTR_216",
    "ATTR_79",
    "ATTR_209",
    "ATTR_335",
    "ATTR_424",
    "ATTR_464",
    "ATTR_59",
    "ATTR_101",
    "ATTR_250",
    "ATTR_140",
    "ATTR_141",
    "ATTR_264",
    "ATTR_378",
    "ATTR_196",
    "ATTR_307",
    "ATTR_388",
    "ATTR_283",
    "ATTR_334"
  ],
  "Material|Composition|Food Grade": [
    "ATTR_387"
  ],
  "Material|Composition|Type": [
    "ATTR_73",
    "ATTR_446"
  ],
  "Material|Composition|Silicone": [
    "ATTR_10",
    "ATTR_144",
    "ATTR_28",
    "ATTR_90",
    "ATTR_285",
    "ATTR_49",
    "ATTR_72",
    "ATTR_224",
    "ATTR_461",
    "ATTR_51",
    "ATTR_286",
    "ATTR_505"
  ],
  "Material|Quality|Overall": [
    "ATTR_16",
    "ATTR_233",
    "ATTR_238",
    "ATTR_377",
    "ATTR_331",
    "ATTR_507",
    "ATTR_24"
  ],
  "Material|Properties|Durability": [
    "ATTR_319"
  ],
  "Material|Quality|Grade": [
    "ATTR_183",
    "ATTR_182",
    "ATTR_261",
    "ATTR_344"
  ],
  "Material|Properties|Stretchiness": [
    "ATTR_433"
  ],
  "Material|Properties|Stain Resistance": [
    "ATTR_330",
    "ATTR_347"
  ],
  "Material|Properties|Strength": [
    "ATTR_393",
    "ATTR_471",
    "ATTR_158"
  ],
  "Material|Properties|Cleanliness": [
    "ATTR_353",
    "ATTR_348",
    "ATTR_352"
  ],
  "Material|Properties|Malleability": [
    "ATTR_436"
  ],
  "Physical Properties|Softness": [
    "ATTR_58",
    "ATTR_354"
  ],
  "Physical Properties|Uniformity": [
    "ATTR_480"
  ],
  "Physical Properties|Weight": [
    "ATTR_488",
    "ATTR_221"
  ],
  "Manufacturing:Origin": [
    "ATTR_510"
  ],
  "Sensory Characteristics|Taste|Neutral": [
    "ATTR_246"
  ],
  "Sensory Characteristics|Odor|Neutral": [
    "ATTR_485",
    "ATTR_232",
    "ATTR_271",
    "ATTR_245"
  ],
  "Sensory Characteristics|Taste|Chemical": [
    "ATTR_247"
  ],
  "Sensory Characteristics|Odor|Slight": [
    "ATTR_270"
  ],
  "Sensory Characteristics|Odor|Strong|Chemical": [
    "ATTR_302",
    "ATTR_124",
    "ATTR_244",
    "ATTR_328",
    "ATTR_451"
  ],
  "Sensory Characteristics|Odor|Strong|Gasoline": [
    "ATTR_290"
  ],
  "Sensory Characteristics|Odor|Strong|Unpleasant": [
    "ATTR_466"
  ],
  "Sensory Characteristics|Odor|Strong|Toxic": [
    "ATTR_486"
  ],
  "Accessories|Fasteners": [
    "ATTR_87"
  ],
  "Accessories|Clamps": [
    "ATTR_299"
  ],
  "Color|Purple": [
    "ATTR_326",
    "ATTR_396"
  ],
  "Color|Red": [
    "ATTR_92"
  ],
  "Color|Green": [
    "ATTR_98",
    "ATTR_53"
  ],
  "Color|Yellow": [
    "ATTR_227",
    "ATTR_95"
  ],
  "Color|Color Options": [
    "ATTR_408",
    "ATTR_228",
    "ATTR_297"
  ],
  "Color|Black": [
    "ATTR_35",
    "ATTR_54"
  ],
  "Color|Original Match": [
    "ATTR_375",
    "ATTR_465",
    "ATTR_170",
    "ATTR_186"
  ],
  "Quantity|Bulk": [
    "ATTR_31"
  ],
  "Quantity|Small Amount": [
    "ATTR_194"
  ],
  "Quantity|Sufficient": [
    "ATTR_341"
  ],
  "Physical Characteristics|Markings": [
    "ATTR_135"
  ],
  "Physical Characteristics|Internal Structure": [
    "ATTR_512"
  ],
  "Durability|Performance": [
    "ATTR_122"
  ],
  "Other": [
    "ATTR_133",
    "ATTR_508"
  ],
  "Quality|Overall": [
    "ATTR_300"
  ],
  "Quality|Condition": [
    "ATTR_410"
  ],
  "Surface Condition|Appearance|Clean": [
    "ATTR_126",
    "ATTR_478"
  ],
  "Visual Characteristics:Appearance": [
    "ATTR_397",
    "ATTR_298",
    "ATTR_69"
  ],
  "Surface Condition|Coating:Slimy": [
    "ATTR_289"
  ],
  "Surface Condition|Appearance|No Branding": [
    "ATTR_288"
  ],
  "Surface Condition|Appearance|Industrial": [
    "ATTR_501"
  ],
  "Surface Condition|Appearance|Kinks": [
    "ATTR_252",
    "ATTR_458"
  ],
  "Surface Condition|Edges:Appearance": [
    "ATTR_418",
    "ATTR_445"
  ],
  "Surface Condition|Self-adhesive": [
    "ATTR_37"
  ],
  "Surface Condition|Stickiness:Material Properties": [
    "ATTR_487",
    "ATTR_406",
    "ATTR_427",
    "ATTR_455"
  ],
  "Surface Condition|Finish:Quality": [
    "ATTR_222"
  ],
  "Safety:Certification": [
    "ATTR_303"
  ]
}