{"use_0": {"+": {"?": ["R1I1WCCWT1NT2"]}}, "use_1": {"+": {"ATTR_0": ["R3I8VR341GZ4RB"]}}, "use_2": {"+": {"?": ["R1KVAHEI120NHI"]}}, "use_3": {"-": {"ATTR_6": ["RVSTA9HODLRVK"]}}, "use_4": {"+": {"?": ["R31XQPAVHE96IP"]}}, "use_5": {"+": {"?": ["R6396V20SZSZT"]}}, "use_6": {"+": {"?": ["R3A69CKNJ7BPR8"]}}, "use_7": {"-": {"ATTR_7": ["R1TTZ2PXF7QHF3"]}}, "use_8": {"+": {"?": ["RRB90JNK12TOC"]}}, "use_9": {"+": {"perf_3": ["R2PXYRWP5ETIUE"]}}, "use_10": {"+": {"?": ["R2SZ0UZVCOTBPD"]}}, "use_11": {"+": {"perf_4": ["RN3G78NRTZ8NQ"]}}, "use_12": {"+": {"?": ["RYRGLPDU9WUJC"]}}, "use_13": {"-": {"ATTR_14": ["RRKV6MWI30SJC"]}}, "use_14": {"+": {"ATTR_13": ["R1U6M5NBRRK9RG"], "ATTR_163": ["R1YXBFGK0I0V1S"], "perf_328": ["R3HZT7OP6C91SL", "RCB9OS4HP4RHZ", "R3TTLLFU1A2CF4", "R2WLB27XIIX8JS", "R2QHMIV6R7VKOV", "R3Q65473BMVYLS", "RM5Q5NMFCKRLB", "R3KIZDSYCG3C1T", "R1FTHSK8S6KAWN", "R1QQRDANN681R7"], "perf_330": ["R3HZT7OP6C91SL"], "perf_331": ["R3Q65473BMVYLS", "RM5Q5NMFCKRLB", "R3KIZDSYCG3C1T", "R1QQRDANN681R7"]}}, "use_15": {"+": {"ATTR_13": ["R2UM9EZDMUHQDM"]}}, "use_16": {"+": {"ATTR_16": ["R26RPRA6P8IK1E"]}}, "use_17": {"+": {"?": ["R37MIGHXSN1MR8"]}}, "use_18": {"+": {"perf_10": ["R1Z29X373DXZ1Y"]}}, "use_19": {"+": {"perf_10": ["R2MAZW4WRSONHG"]}}, "use_20": {"+": {"perf_14": ["R15546UUMHKR7S"]}}, "use_21": {"+": {"perf_15": ["R9JTUJTHEQZV4"]}}, "use_22": {"+": {"?": ["R1CWZPSH021JV6"]}}, "use_23": {"+": {"perf_17": ["R2EOSNHNMR4GA5", "R2AISXJ03JKOKB", "R2HA44Y9OKJ0A7", "R3AJF2X363PKBG", "R27YILU0IX91XD", "R7V4SA3AT8KCK", "R169ONTL41GEXS", "R33XMYCHHW860C"], "perf_23": ["R2AISXJ03JKOKB"], "?": ["R1FG4SP13VQL8R"]}}, "use_24": {"+": {"perf_22": ["R1NHLDAJ2V67HI"], "?": ["R3AJF2X363PKBG", "R1FG4SP13VQL8R", "R2Q3MY8DNUPYIE", "RMTG3ZK7NR3A3", "R169ONTL41GEXS"]}}, "use_25": {"+": {"perf_17": ["RADCHP8MEHLHB"], "perf_20": ["RADCHP8MEHLHB"]}}, "use_26": {"+": {"?": ["R11OZ6TY1VXVK2"]}}, "use_27": {"+": {"perf_21": ["RMIQZAQB0YC1S"], "perf_17": ["RMIQZAQB0YC1S"]}}, "use_28": {"-": {"perf_19": ["R111N04TAA0MDL"]}}, "use_29": {"+": {"perf_17": ["R2Q3MY8DNUPYIE"], "perf_24": ["R2Q3MY8DNUPYIE"]}}, "use_30": {"+": {"perf_24": ["RMTG3ZK7NR3A3"]}}, "use_31": {"+": {"?": ["R1QJCLOR90MN5V"]}}, "use_32": {"+": {"?": ["R33JKZRVVWEIP8"]}}, "use_33": {"+": {"?": ["R2X42DXDGUHOQ5"]}}, "use_34": {"+": {"?": ["RSQQEZT7VJEI8"]}}, "use_35": {"+": {"ATTR_36": ["R2C9UYS2KZNQQT"]}}, "use_36": {"+": {"?": ["R3L3VFT795PITD"]}}, "use_37": {"+": {"?": ["RSTIBZ5E16KKI"]}}, "use_38": {"+": {"?": ["RWXYIVCLUHVSZ"]}}, "use_39": {"+": {"perf_29": ["R32S3JCJK2NS2Z"]}}, "use_40": {"+": {"?": ["RPTOS3R63QY3V"]}}, "use_41": {"+": {"?": ["R29HZY3WLL8IDH"]}}, "use_42": {"+": {"?": ["REXFLWJY43VLU", "RPUN7L93752LS"], "perf_171": ["R1KHLM0YKNYYT2"]}, "-": {"ATTR_33": ["RT1NTRXL445OP"], "ATTR_188": ["R1MO9QD64FNH8K"], "ATTR_309": ["RS3T0PEXJMMGL"]}}, "use_43": {"+": {"?": ["R30CNT37JRQGZL"]}}, "use_44": {"+": {"?": ["R3FWVE8FHLLVA8"]}}, "use_45": {"+": {"?": ["RTN9414VIDIPM"]}}, "use_46": {"+": {"perf_31": ["RXO5KTAI65BK3"]}}, "use_47": {"+": {"?": ["R29522WNK3QNPV"], "ATTR_324": ["R32AD5PZ9AOVVP"]}}, "use_48": {"+": {"ATTR_40": ["RPJTYQOFJSFAF"], "ATTR_49": ["RPJTYQOFJSFAF"]}}, "use_49": {"+": {"ATTR_41": ["R1MDEFAN3I4NN7"], "ATTR_49": ["R1MDEFAN3I4NN7"]}}, "use_50": {"+": {"ATTR_49": ["R1U1XZGNSL9XIV"], "perf_32": ["R1U1XZGNSL9XIV"]}}, "use_51": {"+": {"ATTR_43": ["R2MFYBSZGXFHS5"], "ATTR_49": ["R2MFYBSZGXFHS5"], "perf_32": ["R2MFYBSZGXFHS5"], "perf_34": ["R2MFYBSZGXFHS5"], "perf_42": ["R2MFYBSZGXFHS5"]}}, "use_52": {"+": {"ATTR_44": ["RH7OSD40ZJ7ZZ"], "ATTR_49": ["RH7OSD40ZJ7ZZ"], "perf_32": ["RH7OSD40ZJ7ZZ"], "perf_34": ["RH7OSD40ZJ7ZZ"], "perf_35": ["RH7OSD40ZJ7ZZ"]}}, "use_53": {"+": {"ATTR_45": ["R1XNSF8VLZK850"], "ATTR_49": ["R1XNSF8VLZK850"], "perf_32": ["R1XNSF8VLZK850"], "perf_6": ["R1XNSF8VLZK850"], "perf_36": ["R1XNSF8VLZK850"], "perf_37": ["R1XNSF8VLZK850"], "perf_38": ["R1XNSF8VLZK850"]}}, "use_54": {"+": {"ATTR_45": ["R1XNSF8VLZK850"], "ATTR_49": ["R1XNSF8VLZK850"], "perf_32": ["R1XNSF8VLZK850"], "perf_6": ["R1XNSF8VLZK850"], "perf_36": ["R1XNSF8VLZK850"], "perf_37": ["R1XNSF8VLZK850"], "perf_38": ["R1XNSF8VLZK850"]}}, "use_55": {"+": {"ATTR_45": ["R1XNSF8VLZK850"], "ATTR_49": ["R1XNSF8VLZK850"], "perf_32": ["R1XNSF8VLZK850"], "perf_6": ["R1XNSF8VLZK850"], "perf_36": ["R1XNSF8VLZK850"], "perf_37": ["R1XNSF8VLZK850"], "perf_38": ["R1XNSF8VLZK850"]}}, "use_56": {"+": {"ATTR_45": ["R1XNSF8VLZK850"], "ATTR_49": ["R1XNSF8VLZK850"], "perf_32": ["R1XNSF8VLZK850"], "perf_6": ["R1XNSF8VLZK850"], "perf_36": ["R1XNSF8VLZK850"], "perf_37": ["R1XNSF8VLZK850"], "perf_38": ["R1XNSF8VLZK850"]}}, "use_57": {"+": {"ATTR_46": ["RCL5NOXPPT4J6"], "ATTR_49": ["RCL5NOXPPT4J6"]}}, "use_58": {"+": {"ATTR_48": ["RHXE9CB35PII8"], "ATTR_49": ["RHXE9CB35PII8"], "ATTR_54": ["RHXE9CB35PII8"], "ATTR_57": ["RHXE9CB35PII8"], "perf_38": ["RHXE9CB35PII8"], "perf_39": ["RHXE9CB35PII8"], "perf_40": ["RHXE9CB35PII8"]}}, "use_59": {"-": {"ATTR_51": ["R1H8IGMXOKQ9IF"], "perf_44": ["R1H8IGMXOKQ9IF"]}}, "use_60": {"-": {"perf_49": ["R2CQQNI5C9EE9C"]}}, "use_61": {"-": {"ATTR_71": ["R3EV6KDZF7NN17"]}}, "use_62": {"+": {"ATTR_28": ["R2CMJFOKDYGDBJ"]}}, "use_63": {"+": {"perf_46": ["R14SAWUFR6OLLR"], "perf_55": ["R14SAWUFR6OLLR"]}}, "use_64": {"-": {"perf_48": ["R3DSL3H2QYDDNK"]}}, "use_65": {"-": {"perf_49": ["R2MUYYHIJ3FC2N"]}}, "use_66": {"+": {"perf_57": ["R34A4VXCX7JMBN"]}}, "use_67": {"+": {"?": ["R2JWZL3H0BNT8U", "R3QS2D8HFPE12Z"]}}, "use_68": {"-": {"perf_58": ["RDUD3HW56NSBW"]}}, "use_69": {"+": {"?": ["RT3VLMCMMWRA"]}}, "use_70": {"+": {"?": ["R29BRZWM4M1C6T"]}}, "use_71": {"+": {"?": ["RF86P0LW9I50O"]}}, "use_72": {"+": {"?": ["R7ZKO7W2K217Y"]}}, "use_73": {"-": {"perf_61": ["R1LHMRGARLDWEX"], "perf_62": ["R1LHMRGARLDWEX"]}}, "use_74": {"+": {"perf_63": ["R24Q3XK0RWQ59Q"], "perf_68": ["R24Q3XK0RWQ59Q"]}}, "use_75": {"+": {"perf_63": ["R1OGH9F2UUMST7"]}}, "use_76": {"+": {"perf_63": ["R31SGB2KRLMDDC"], "ATTR_87": ["R31SGB2KRLMDDC"]}}, "use_77": {"+": {"perf_63": ["R3BCRN7SDIX4V5"], "ATTR_86": ["R3BCRN7SDIX4V5"]}}, "use_78": {"+": {"perf_63": ["R2QN52IIKL4ZOB"], "perf_71": ["R2QN52IIKL4ZOB"], "perf_72": ["R2QN52IIKL4ZOB"]}}, "use_79": {"+": {"perf_63": ["R190I21TCUR2UA"], "perf_69": ["R190I21TCUR2UA"], "perf_73": ["R190I21TCUR2UA"]}}, "use_80": {"+": {"perf_63": ["R2DEHIKWQLFULQ"], "perf_74": ["R2DEHIKWQLFULQ"]}}, "use_81": {"+": {"perf_63": ["R1F543I7YS0OTE"], "perf_71": ["R1F543I7YS0OTE"], "ATTR_12": ["R1F543I7YS0OTE"]}}, "use_82": {"-": {"perf_65": ["R1UC3PMKCV6PXO"]}}, "use_83": {"+": {"perf_63": ["RSFWOQK2V8K6R"], "ATTR_82": ["RSFWOQK2V8K6R"]}}, "use_84": {"-": {"perf_66": ["R3P5SJKWQNAKMH"]}}, "use_85": {"+": {"perf_63": ["R3HDU2UI6214VJ"], "perf_70": ["R3HDU2UI6214VJ"], "ATTR_81": ["R3HDU2UI6214VJ"]}}, "use_86": {"-": {"ATTR_79": ["R1JT5GUXRTLWMN"]}}, "use_87": {"+": {"?": ["R11ZO11IWAGUQ4"]}}, "use_88": {"+": {"perf_75": ["R1TWUM5WFUKNS0"], "perf_78": ["R34FAW37FUGEYK", "R31MVI1KOB7E1B"]}}, "use_89": {"+": {"?": ["R17KBEPBSOK76L"]}}, "use_90": {"+": {"?": ["R1I2WR9ZGW2NWJ", "R140R06SNNY7LX"]}}, "use_91": {"+": {"ATTR_89": ["R3Q7PDQUFKIV8E"]}}, "use_92": {"+": {"ATTR_88": ["RS9R4CAZ1PF07"]}}, "use_93": {"-": {"perf_82": ["R17N3GQH0NKC5P"], "perf_83": ["R17N3GQH0NKC5P"]}}, "use_94": {"+": {"?": ["R10H3A67FQEKCB"]}}, "use_95": {"+": {"?": ["R2CY6S94IB33O4"]}}, "use_96": {"-": {"perf_76": ["R347FOLO3T8PPI"]}}, "use_97": {"+": {"perf_77": ["R2NU51ISJA3TI2"], "perf_79": ["R2NU51ISJA3TI2"]}}, "use_98": {"+": {"perf_78": ["R2AM906YK9VJ9S"], "ATTR_92": ["R2AM906YK9VJ9S"]}}, "use_99": {"-": {"ATTR_96": ["R22OSWKFXKMHA3"]}}, "use_100": {"-": {"ATTR_100": ["R3UC9L4A8IWSSB"], "perf_91": ["R3UC9L4A8IWSSB"]}}, "use_101": {"-": {"ATTR_98": ["R2WMFQ0SM366HH"]}}, "use_102": {"+": {"?": ["R1QLJCXV4DYIHB"]}}, "use_103": {"+": {"perf_85": ["R1J7CT8IP4JLYI"], "perf_87": ["R1J7CT8IP4JLYI"]}}, "use_104": {"-": {"ATTR_93": ["R33EB3FV5OUZ88"]}}, "use_105": {"+": {"perf_86": ["R1CRGXGEL6VH1K"]}}, "use_106": {"-": {"ATTR_110": ["R3TLR5UAAY3SSY"], "perf_92": ["R3TLR5UAAY3SSY"], "perf_93": ["R3TLR5UAAY3SSY"]}, "+": {"perf_267": ["R3QSG9JNDLCMMH"], "ATTR_294": ["RAFMTJ3GKR7JP"]}}, "use_107": {"+": {"ATTR_104": ["R16ZCBSPO0AV7F"], "ATTR_108": ["R16ZCBSPO0AV7F"], "perf_96": ["R16ZCBSPO0AV7F"], "perf_32": ["R16ZCBSPO0AV7F"], "ATTR_107": ["R16ZCBSPO0AV7F"]}}, "use_108": {"+": {"ATTR_112": ["R2PG655U2DLX96"], "perf_95": ["R2PG655U2DLX96"]}}, "use_109": {"+": {"ATTR_111": ["R31TGIH0KU8UW2"], "perf_99": ["R31TGIH0KU8UW2"], "perf_100": ["R31TGIH0KU8UW2"], "perf_102": ["R31TGIH0KU8UW2"]}}, "use_110": {"+": {"?": ["R3M7A9A8NZRRAP"]}}, "use_111": {"+": {"perf_32": ["R1M4JOL2XXZUJF"], "perf_101": ["R1M4JOL2XXZUJF"]}, "-": {"perf_418": ["R339QK8N9JH8L3"]}}, "use_112": {"+": {"ATTR_105": ["R3CG06BA0UDP8Q"]}}, "use_113": {"+": {"ATTR_111": ["R2DAM1KRQSTSFM"]}}, "use_114": {"+": {"perf_40": ["R3GCCGGHY53Q0V"]}}, "use_115": {"+": {"perf_104": ["R2810XVRK2B2B8"], "perf_106": ["R2810XVRK2B2B8"], "perf_107": ["R2810XVRK2B2B8"], "perf_77": ["R2810XVRK2B2B8"], "perf_109": ["R2810XVRK2B2B8"]}}, "use_116": {"+": {"?": ["R571WR0E3PYQN"]}}, "use_117": {"+": {"?": ["R28SSZTYVHMLRY"]}}, "use_118": {"+": {"perf_104": ["R2AD7AWOQEW9QA", "R2QGXKFAB7UGM2"], "perf_106": ["R2AD7AWOQEW9QA"], "perf_111": ["R2AD7AWOQEW9QA"]}}, "use_119": {"+": {"perf_104": ["R2TY2770L2ZCWY"]}}, "use_120": {"+": {"perf_106": ["R6RCA3C6WTVF5"], "ATTR_91": ["R6RCA3C6WTVF5"]}}, "use_121": {"+": {"perf_106": ["R6RCA3C6WTVF5"], "ATTR_91": ["R6RCA3C6WTVF5"]}, "-": {"perf_112": ["R2EIXAVH6DIR1V"]}}, "use_122": {"+": {"?": ["R6RCA3C6WTVF5"]}}, "use_123": {"+": {"perf_104": ["R2FR8HE3IHMQKE"], "perf_106": ["R2FR8HE3IHMQKE"]}}, "use_124": {"+": {"ATTR_116": ["RTJWMHH6QAKVZ"]}}, "use_125": {"+": {"ATTR_34": ["RBJVLM47W0ZA7"]}}, "use_126": {"+": {"perf_114": ["RUS0FK1C23CGN"], "perf_115": ["RUS0FK1C23CGN"]}}, "use_127": {"+": {"?": ["R3EO4FH0TUII9R"]}}, "use_128": {"+": {"perf_117": ["R1RSHDNN16T5L2"]}}, "use_129": {"+": {"?": ["R15B8PJX905ZBP"]}}, "use_130": {"+": {"?": ["R37QX8H202VHV4"]}}, "use_131": {"-": {"perf_120": ["R3V3TC4E930SYY"]}}, "use_132": {"+": {"ATTR_127": ["RJFIBZBJQ2A98"]}}, "use_133": {"+": {"?": ["R3888X48ENWQBL"]}}, "use_134": {"+": {"perf_122": ["R1B7UX3FDUBPSM", "R2K06FDY8QXBHS", "R1KR4U3E8ZCNYK"], "perf_209": ["R2Z61NOAVVDCLP"]}}, "use_135": {"+": {"perf_126": ["R100TU03PRVA6V"]}}, "use_136": {"+": {"ATTR_138": ["R129LK2AEAQK88"]}}, "use_137": {"+": {"perf_4": ["R2K06FDY8QXBHS"]}}, "use_138": {"+": {"?": ["RSEXOUVNATXP7"]}}, "use_139": {"+": {"?": ["R24JNLRY8KM94"]}}, "use_140": {"+": {"?": ["R39V0S4BH5GS7H"]}}, "use_141": {"+": {"perf_123": ["R31FTF6NF7HDWO"]}}, "use_142": {"+": {"?": ["R1LBCUQ5HNVHT4"]}}, "use_143": {"+": {"ATTR_141": ["R22BV6IA50H5SC"]}}, "use_144": {"-": {"ATTR_133": ["R3GX22SVTZGMJQ"]}}, "use_145": {"+": {"perf_139": ["R196RURLLKYNQL"]}}, "use_146": {"+": {"?": ["R39M4MNEL6RSZR"]}}, "use_147": {"-": {"perf_134": ["R3NYNT23EFHIAR"]}}, "use_148": {"+": {"?": ["R2VEZWTFFC786X"]}}, "use_149": {"-": {"ATTR_147": ["R2XWPN7RI4MNUP"]}}, "use_150": {"+": {"?": ["RVSWXWD6SEJ6"]}}, "use_151": {"+": {"?": ["RVSWXWD6SEJ6"]}}, "use_152": {"+": {"?": ["R21JXDSM8GYF4M"]}}, "use_153": {"+": {"ATTR_33": ["R2YFPJVBJ8HYMW"]}}, "use_154": {"+": {"ATTR_33": ["R1372WSBMBXECS"]}}, "use_155": {"+": {"perf_96": ["R2955SLIMSISBW"]}}, "use_156": {"-": {"perf_142": ["R156OALUY5D858"]}}, "use_157": {"+": {"ATTR_33": ["RS58BRW7W22WS"]}}, "use_158": {"+": {"?": ["R2WY1MF6471RFI"]}}, "use_159": {"+": {"perf_145": ["R3NNTVQEXM7IXA"]}}, "use_160": {"+": {"perf_144": ["R1YL9WKYLPGGNJ", "RPHG9QB5DFC4"]}}, "use_161": {"+": {"?": ["R1YS6XSSM4FC6C"]}}, "use_162": {"+": {"?": ["R343G8TWTGCBJS", "R1L00EVL7J8L1O", "RNXRJL3D1RI5D", "R1EN3RJKLEDMAZ"]}}, "use_163": {"+": {"?": ["R121QD3UA1EYHJ"]}}, "use_164": {"+": {"ATTR_157": ["RVYDBFXZUZFU8"], "ATTR_158": ["RVYDBFXZUZFU8"], "ATTR_159": ["RVYDBFXZUZFU8"], "ATTR_161": ["RVYDBFXZUZFU8"], "ATTR_162": ["RVYDBFXZUZFU8"]}}, "use_165": {"+": {"perf_147": ["R23C83I3VKV4QD"]}}, "use_166": {"+": {"ATTR_163": ["R1S4SDHCP9MLU"]}}, "use_167": {"+": {"perf_148": ["R3TW1IWD1TKVF8"], "perf_151": ["R3TW1IWD1TKVF8"]}}, "use_168": {"+": {"ATTR_157": ["R22I3GRNT0F24F"], "ATTR_160": ["R22I3GRNT0F24F"], "ATTR_161": ["R22I3GRNT0F24F"], "perf_149": ["R22I3GRNT0F24F"]}}, "use_169": {"+": {"?": ["RBMN5DUE0V77C"]}}, "use_170": {"+": {"ATTR_163": ["R1EN3RJKLEDMAZ"]}}, "use_171": {"+": {"ATTR_163": ["R1LNKP76VCCL0W"], "perf_152": ["R1LNKP76VCCL0W"]}}, "use_172": {"+": {"ATTR_157": ["R1CF8974QQR0TC"], "ATTR_163": ["R1CF8974QQR0TC"]}}, "use_173": {"+": {"?": ["R1Y340DU6BDHB1"]}}, "use_174": {"+": {"?": ["RXMEC9352FPQO"]}}, "use_175": {"+": {"perf_150": ["R1HYM1KMAGZAI2"]}}, "use_176": {"+": {"perf_32": ["R3ARYBGFGJQ2ZA"], "perf_155": ["R3ARYBGFGJQ2ZA"]}}, "use_177": {"+": {"ATTR_164": ["RJN8CQ94S9621"], "ATTR_170": ["RJN8CQ94S9621"]}}, "use_178": {"-": {"ATTR_167": ["R1US39DLFWJ060"], "perf_94": ["R1US39DLFWJ060"], "perf_156": ["R1US39DLFWJ060"], "perf_238": ["R7UTNBFTAKT8"], "perf_243": ["R7UTNBFTAKT8"], "ATTR_416": ["R3HAHL5RDL25TW"]}, "+": {"ATTR_239": ["R3HDZMKIENIDF8"], "perf_309": ["R3L3MOB5DES647"], "perf_314": ["RMQPFMIVEEPZZ", "RONQS6R1NUO0J", "R1Z3ZN8KZ9RSDL", "R160RKZIXP6VIR"], "?": ["RU18ETKSK37Z0", "R1U5T4EVGPD8LV", "R3TZ78XGCETS32"], "perf_405": ["RJH91JRTRMZAI"], "perf_408": ["RJH91JRTRMZAI"], "perf_414": ["RJH91JRTRMZAI"]}}, "use_179": {"+": {"?": ["R24NHGOPZVSI5A", "R30KV3FWUVNUPQ", "R2TDC0ZUETSI1X", "RNU5IUP7SMTDH", "R3M7RVGOWVH3IC", "R26UX579FP8601", "R5LE5KMO7ZFB7", "R3CH690Q26VW6M"]}}, "use_180": {"+": {"?": ["R3T6VZ435103RK"]}}, "use_181": {"+": {"?": ["R1TAAJIBBNDXV5"]}}, "use_182": {"+": {"?": ["R23LYKDEFX25Q3"]}}, "use_183": {"+": {"perf_32": ["R12XHD0F5XLOLP"], "?": ["R205LOLGFPTWUX"]}}, "use_184": {"+": {"?": ["R30Q326XHUYGP", "R8GU5BUYICUZ5", "R6Q2P7KI3Q5QH"]}}, "use_185": {"-": {"?": ["RKCSYDDAKL4I3"]}}, "use_186": {"+": {"?": ["R191F27S9LL1NT"]}}, "use_187": {"+": {"?": ["R3ONXKTPE7IOLB"]}}, "use_188": {"+": {"?": ["R3S9EB8TPTK6S4", "R3SDZVLELL8P2A", "R1YYYJ6WA4XVWG"]}}, "use_189": {"-": {"perf_32": ["R39K68FZ11SCIA"]}}, "use_190": {"-": {"?": ["R2FBMEN7WOGNW1"]}, "+": {"perf_326": ["R1U7FN7NHG8TD0"]}}, "use_191": {"+": {"?": ["R2UZWCXWG6MFD3"]}}, "use_192": {"+": {"?": ["R3TIQQPI9AP3XF"]}}, "use_193": {"+": {"?": ["R3P1FRV9VLENMA"]}}, "use_194": {"+": {"?": ["R3P1FRV9VLENMA"]}}, "use_195": {"+": {"?": ["R1CU97PAFD0LNH"]}}, "use_196": {"+": {"perf_170": ["R2J9OLLKGNPEHX"]}}, "use_197": {"+": {"?": ["R334HJ6CUMK453"]}}, "use_198": {"+": {"ATTR_181": ["R1M2B73BMY3RNH"]}}, "use_199": {"+": {"perf_171": ["R12WZXPMDZ7PDI"]}}, "use_200": {"+": {"perf_171": ["R29717OSE363R8", "R2ZJM4WKERBDO1", "R5AZSYQPRWT4I"]}}, "use_201": {"+": {"perf_171": ["R5AZSYQPRWT4I"]}}, "use_202": {"+": {"perf_171": ["R3Q7CMCQ7M62CS"]}}, "use_203": {"+": {"perf_171": ["R3Q7CMCQ7M62CS"]}}, "use_204": {"+": {"ATTR_34": ["R3L4ZHDAOZ6I77", "R30OY3ZRHMBCAT", "R1W5GYHQYMN8BQ", "R1IIIY3PFJNCT9", "R3CSXEN1MS6G5C"], "ATTR_210": ["R1J8LSWQKNMGBM"], "?": ["R1CLCZYP3TCFYU", "RPDEZ4QTFVK3X", "R1HVNDUVGO5BXJ", "R34A1LN1JFSAZ", "R3FJS1PA4LQ7P", "R2MAL39Y8SS4IK", "R106QRGLE9RKLV"], "ATTR_49": ["R3CH54GSO4WFCL"], "perf_193": ["R350VIOFHXROXJ"], "perf_32": ["RLDG1BUBMQZSN"]}}, "use_205": {"+": {"ATTR_34": ["R30OY3ZRHMBCAT"]}, "-": {"perf_182": ["R19DMSBCYVHRKN"]}}, "use_206": {"+": {"ATTR_34": ["R3CSXEN1MS6G5C"]}}, "use_207": {"-": {"ATTR_196": ["R2RQBOIKJKZ7H"], "ATTR_198": ["R3RXOMPQ4TEGKG", "RCE2F8R074UVU", "R2C6MXOVLKD6HZ"]}}, "use_208": {"-": {"ATTR_203": ["R3N0N4TY0PAIXQ"]}}, "use_209": {"+": {"perf_186": ["R1H79D6BAOJ0B4"]}}, "use_210": {"+": {"perf_186": ["R3SZ85INN14N0Y"]}}, "use_211": {"+": {"perf_186": ["R38JP72C9DXTC2"], "perf_170": ["R38JP72C9DXTC2"]}}, "use_212": {"+": {"ATTR_212": ["R6BHXONFN9NEN"], "?": ["R1UURWV1R9B7UA"], "perf_464": ["R3U5MUQCW2KQI4"]}}, "use_213": {"-": {"ATTR_213": ["R3QLO5FI6918UH"]}}, "use_214": {"+": {"perf_191": ["R3HCR80T5KVC9B"]}}, "use_215": {"+": {"?": ["R3D8BMKCEM5DBN"]}}, "use_216": {"-": {"perf_189": ["R3D8BMKCEM5DBN"]}}, "use_217": {"-": {"perf_192": ["R2T3J8GMXILBI7"]}}, "use_218": {"+": {"perf_188": ["R3MP53RRPTPX3O"]}}, "use_219": {"-": {"perf_192": ["R1SF6AB561FUZB"]}}, "use_220": {"+": {"?": ["R1WR7VOWKRCD1L"]}}, "use_221": {"+": {"ATTR_212": ["R8XIJ2SUUWFRU"]}}, "use_222": {"+": {"?": ["R248PRI8JY9EG2"]}}, "use_223": {"+": {"?": ["R2MDYSTAQOK1CR"]}}, "use_224": {"+": {"perf_195": ["R3F7KHAHDENPZ0"]}}, "use_225": {"+": {"?": ["R3EVSML6ZKI6MF"]}}, "use_226": {"+": {"?": ["R1ED2VM38IHBQE"]}}, "use_227": {"+": {"perf_203": ["R27BVAUDN01SRA"]}}, "use_228": {"+": {"perf_198": ["RFAXW8QARZ9UD"], "perf_204": ["RFAXW8QARZ9UD"]}}, "use_229": {"+": {"perf_32": ["R2F19QWEXOR9M6"], "perf_202": ["R2F19QWEXOR9M6"]}}, "use_230": {"+": {"perf_204": ["R1XBJOYWK879KF"]}}, "use_231": {"+": {"perf_203": ["R1Y2ARKVJTGOSL"]}}, "use_232": {"+": {"?": ["RF5X5FZ69YP6P"]}}, "use_233": {"+": {"?": ["R2UORK7DI171EO"]}}, "use_234": {"+": {"?": ["R1E738LUPS0DBB"]}}, "use_235": {"+": {"?": ["R211O7S5VOEGHQ"]}}, "use_236": {"+": {"?": ["R31AK5YF87CW4H"]}}, "use_237": {"+": {"?": ["RSMCD7XW0QKRJ"]}}, "use_238": {"+": {"?": ["R3PYUF35QESCWT"]}}, "use_239": {"+": {"perf_205": ["R3JQQJ9BF4DEEL"]}}, "use_240": {"-": {"perf_201": ["RHS1LUFX5O9MY"]}}, "use_241": {"+": {"?": ["R1LNJLT2IA3BQ"]}}, "use_242": {"+": {"perf_207": ["R2Z4TCRZV9CPSK"]}}, "use_243": {"+": {"?": ["R12CJ4L910SA39"]}}, "use_244": {"+": {"perf_206": ["R2SPX4M8HFA1XN"]}}, "use_245": {"+": {"?": ["R1OHKAKJN98PYZ", "R28QHBQ912WHV7", "R11G3CKJTQPQ73"]}}, "use_246": {"+": {"?": ["R8HZDI7Z98WJA"], "perf_170": ["R33UQRGGFUF5RV"]}, "-": {"perf_211": ["RTYQECMVQ7OB7"]}}, "use_247": {"+": {"perf_4": ["R3PUCO43FI2IBD"], "perf_95": ["R3PUCO43FI2IBD"]}}, "use_248": {"-": {"perf_210": ["R1K7D2AYRC1DJX"]}}, "use_249": {"+": {"perf_4": ["RTKC1OQ0O3CK1"]}}, "use_250": {"+": {"perf_6": ["RMPVXHC1404RP"], "perf_216": ["RMPVXHC1404RP"]}}, "use_251": {"-": {"ATTR_247": ["R14ECWD8HI62IH"]}}, "use_252": {"+": {"?": ["R2Z51IKZDXDWDX"]}}, "use_253": {"+": {"perf_217": ["R353WSJ4EL4K2T"]}}, "use_254": {"+": {"ATTR_246": ["R17OQN7U6G4I6W"]}}, "use_255": {"+": {"?": ["RIJ6VOABI9DV0"]}}, "use_256": {"+": {"ATTR_239": ["R3LQZ4GCTU1JNI"]}}, "use_257": {"+": {"?": ["RNHS1QRJR3UQF"]}}, "use_258": {"+": {"?": ["RGIT37G3R5EAF"]}}, "use_259": {"+": {"ATTR_239": ["R105NWFXV3KEF5"], "ATTR_246": ["R105NWFXV3KEF5"]}}, "use_260": {"+": {"ATTR_239": ["RR6D39DHYGRT9"], "ATTR_246": ["RR6D39DHYGRT9"]}}, "use_261": {"-": {"ATTR_241": ["R871I79ZGNFLA"], "ATTR_247": ["R871I79ZGNFLA"]}}, "use_262": {"+": {"perf_216": ["R24Z3FZT6HFDST"], "ATTR_245": ["R24Z3FZT6HFDST"], "ATTR_246": ["R24Z3FZT6HFDST"]}}, "use_263": {"+": {"?": ["R2J24ZEUB7GWE7", "R1TQ2WK8BHRXZ1", "R1POCF3C9Y8CC1"]}}, "use_264": {"+": {"?": ["R14Z9VZRNO4E9M", "R1U7L57J24T9CT"]}}, "use_265": {"+": {"?": ["R26L9WUIYA6TKR"]}}, "use_266": {"+": {"perf_164": ["R3F8YXQAC3E4UZ"]}}, "use_267": {"+": {"ATTR_248": ["R2WR10ZQ1B9BV4"], "ATTR_249": ["R2WR10ZQ1B9BV4"], "ATTR_250": ["R2WR10ZQ1B9BV4"]}}, "use_268": {"+": {"?": ["R1P0KA3BAS4EG4"]}}, "use_269": {"+": {"?": ["R1ZGKW408R9G6X"]}}, "use_270": {"+": {"?": ["RV038G631A1RJ"]}}, "use_271": {"+": {"perf_221": ["R2Z1XACPPN8QT0"]}}, "use_272": {"+": {"perf_227": ["RDR30F2M77WVP"]}}, "use_273": {"+": {"perf_225": ["R1TW6R3E5Y9V3P", "RNXW956FT6QBW"]}}, "use_274": {"+": {"?": ["R19H0EV502KRAJ"]}}, "use_275": {"+": {"?": ["R2V22P6TL44BU0"]}}, "use_276": {"+": {"?": ["R2AYG5YUDID33R"]}}, "use_277": {"+": {"?": ["R2OD2FQXMHXN22"]}}, "use_278": {"+": {"?": ["RPGXPK5Y7DWCK"]}}, "use_279": {"+": {"ATTR_254": ["R3F5ZNX7U3SAMX"]}}, "use_280": {"+": {"ATTR_258": ["R2WF5S6CYJS50S"], "ATTR_157": ["R2WF5S6CYJS50S"]}}, "use_281": {"-": {"perf_233": ["R1OWEE5S0E0C3S"], "ATTR_258": ["R1OWEE5S0E0C3S"]}}, "use_282": {"+": {"ATTR_260": ["R2VYBBDTBHAQ53"]}}, "use_283": {"-": {"ATTR_258": ["R3LO8WEXYVNQVW"], "ATTR_259": ["R3LO8WEXYVNQVW"]}}, "use_284": {"-": {"ATTR_258": ["R3J9Y9H7QOHYFL"], "perf_234": ["R3J9Y9H7QOHYFL"]}}, "use_285": {"+": {"perf_236": ["RNQ7W5I9TR6FH"]}}, "use_286": {"+": {"perf_237": ["R1KQH9SGRM4N8U"], "perf_31": ["R1KQH9SGRM4N8U"]}}, "use_287": {"+": {"perf_237": ["R1L5VMS8QPSVPY"]}}, "use_288": {"+": {"ATTR_34": ["R1WRMLY62QXGU8"], "ATTR_264": ["R1WRMLY62QXGU8"], "ATTR_197": ["R1WRMLY62QXGU8"], "perf_245": ["R1WRMLY62QXGU8"]}}, "use_289": {"-": {"perf_238": ["R2Q3VXVZ372SRP"]}}, "use_290": {"-": {"perf_238": ["RVG9UN8VC5M0G", "R36L51EIKF4QLB"]}}, "use_291": {"+": {"ATTR_197": ["R1NLHGY0ME370X"]}}, "use_292": {"+": {"ATTR_273": ["R5ZHWOW269T96"]}}, "use_293": {"+": {"perf_247": ["R2UYQM24J16TPF"]}}, "use_294": {"+": {"ATTR_277": ["R1HMVWOEJEHW5T"]}}, "use_295": {"+": {"ATTR_277": ["R2WWFCU7BG3RVE"], "perf_164": ["R2WWFCU7BG3RVE"]}}, "use_296": {"-": {"ATTR_275": ["R2BWI18WP0D00P"]}}, "use_297": {"+": {"?": ["R3NWSQXBNBKQ45"]}}, "use_298": {"+": {"ATTR_277": ["R39HWSABZ695XW"], "perf_249": ["R39HWSABZ695XW"]}}, "use_299": {"+": {"perf_248": ["R14V0IDCI56ILZ"]}}, "use_300": {"+": {"perf_248": ["R14V0IDCI56ILZ"]}}, "use_301": {"+": {"perf_252": ["R2474W84K2S1IY"]}}, "use_302": {"+": {"ATTR_283": ["RYZ5OBKX9PP10"], "perf_258": ["RYZ5OBKX9PP10"]}}, "use_303": {"-": {"perf_253": ["R3NA16XIJESBPO", "R5O2AW40FK78H", "R3EI3VGAZRM4PA", "R3I81BDSX4W6ST"]}}, "use_304": {"-": {"perf_251": ["R39W49MXYS5CJO"]}}, "use_305": {"+": {"ATTR_282": ["R4MKT1JDBTXDU"], "perf_254": ["R4MKT1JDBTXDU"]}}, "use_306": {"+": {"perf_257": ["RMFCSIJT66WOK"], "perf_261": ["RMFCSIJT66WOK"], "perf_262": ["RMFCSIJT66WOK"]}}, "use_307": {"+": {"?": ["R348O6I5PEWAAX"]}}, "use_308": {"+": {"?": ["R17ESMDS01E7Y5"]}}, "use_309": {"+": {"perf_32": ["R2DCXMOU4Y4KE0"], "perf_266": ["R13IPXM9L322EX"], "perf_269": ["R50LC1WS2AP9A"], "perf_270": ["R2T19SP3W58RD7"], "perf_271": ["RWKR1M1BWL0X2"]}}, "use_310": {"+": {"perf_266": ["R2N7OYG3B0JSHM"]}}, "use_311": {"+": {"perf_266": ["R111GE5FW0DJQU"]}}, "use_312": {"+": {"ATTR_294": ["R3E971ZQVI4L1N"]}}, "use_313": {"+": {"perf_264": ["RWKR1M1BWL0X2"], "perf_270": ["R2T19SP3W58RD7"]}}, "use_314": {"+": {"perf_32": ["R2DCXMOU4Y4KE0"]}}, "use_315": {"+": {"perf_268": ["R13IPXM9L322EX"]}}, "use_316": {"+": {"ATTR_292": ["R3QGIXO1G3TI1S"], "perf_272": ["R3QGIXO1G3TI1S"], "perf_273": ["R3QGIXO1G3TI1S"], "perf_275": ["R3QGIXO1G3TI1S"], "perf_276": ["R3QGIXO1G3TI1S"]}}, "use_317": {"+": {"perf_6": ["R50LC1WS2AP9A"], "perf_85": ["R50LC1WS2AP9A"], "perf_269": ["R50LC1WS2AP9A"]}}, "use_318": {"+": {"ATTR_296": ["R2R758PRHJJW3P"]}}, "use_319": {"+": {"?": ["R1SCIVPQJM1FQD"]}}, "use_320": {"+": {"perf_266": ["RTV8KGAW154CE"]}}, "use_321": {"+": {"perf_266": ["RTV8KGAW154CE"]}}, "use_322": {"+": {"?": ["R3UA78QHI4WUR7"]}}, "use_323": {"+": {"perf_277": ["RCN3QTW25ZB05"], "perf_278": ["RCN3QTW25ZB05"]}}, "use_324": {"+": {"?": ["R228345Y3RJUAV"]}}, "use_325": {"+": {"?": ["RUF0K1F17P2CF"]}}, "use_326": {"+": {"?": ["R25HJAN97KYUBZ"]}}, "use_327": {"-": {"ATTR_302": ["R3NT03FC28RJWO", "R3OCX6OUDZW12M"], "ATTR_303": ["R1TQMKWHZOG3IK"]}}, "use_328": {"+": {"perf_283": ["R3OCX6OUDZW12M"], "perf_285": ["R3OCX6OUDZW12M"]}}, "use_329": {"+": {"perf_279": ["R3X7UDYF9HQDB"]}}, "use_330": {"+": {"?": ["R229RYUAUKV0ZI"]}}, "use_331": {"+": {"?": ["R1O1KOHPET92D8"]}}, "use_332": {"+": {"?": ["RWU24HC9U7HZN"]}, "-": {"perf_282": ["RWU24HC9U7HZN"]}}, "use_333": {"-": {"perf_280": ["R37P7PHTRI7YM9"], "perf_281": ["R24Z7R168W4Q5"]}}, "use_334": {"-": {"ATTR_311": ["R1D2WZR1PL10S8"]}}, "use_335": {"+": {"ATTR_313": ["R2XZDY2IKD9UEG"]}}, "use_336": {"-": {"ATTR_311": ["R3VML1L4LJ0EQT"]}}, "use_337": {"-": {"ATTR_311": ["R3F6K6SIUOCZ37"]}}, "use_338": {"+": {"perf_6": ["RUYJJSGCBA5OQ"], "ATTR_321": ["RUYJJSGCBA5OQ"]}}, "use_339": {"+": {"perf_6": ["R23Y1XIVACYH36"]}}, "use_340": {"+": {"perf_6": ["R22GW8ZH5ITFUH"]}}, "use_341": {"+": {"perf_6": ["R2BC8VDT1EQRJ7"]}}, "use_342": {"+": {"ATTR_319": ["R3SAFGCUAQZ1L2"], "ATTR_321": ["R3SAFGCUAQZ1L2"]}}, "use_343": {"+": {"perf_116": ["R3CR2PIOGIC7OD"], "perf_295": ["R3CR2PIOGIC7OD"]}}, "use_344": {"+": {"perf_6": ["R2UUR17EXSDQY1"]}}, "use_345": {"+": {"perf_32": ["R2FCFG0RDHLFQX"]}}, "use_346": {"-": {"perf_297": ["RFN2GPK5Y9LR1"]}}, "use_347": {"+": {"?": ["R61YLJ0BOYJHS"]}}, "use_348": {"+": {"?": ["R1VYSVDBTFEQ96"]}}, "use_349": {"+": {"perf_300": ["R2Q3PRPAGFEXIQ"]}}, "use_350": {"+": {"perf_46": ["R189VB3CQ6CW34"]}}, "use_351": {"+": {"?": ["R20X41GGQFCR0N"]}}, "use_352": {"+": {"perf_303": ["R7VIXTBQ1B58T"]}}, "use_353": {"-": {"?": ["R12C85EBX1A75Q"]}}, "use_354": {"-": {"perf_308": ["RDVE072T09X5L"]}}, "use_355": {"+": {"perf_314": ["RMQPFMIVEEPZZ"]}}, "use_356": {"+": {"perf_314": ["RONQS6R1NUO0J"]}}, "use_357": {"+": {"perf_310": ["R1CJ2UE6KBGAYE"]}}, "use_358": {"+": {"ATTR_34": ["R1YYXZGH5YWLHY"], "ATTR_334": ["R1YYXZGH5YWLHY"]}}, "use_359": {"+": {"ATTR_332": ["R3H4RBK2R0V7KA"], "ATTR_336": ["R3H4RBK2R0V7KA"]}}, "use_360": {"+": {"?": ["R2G5IEPHZIIBX7"]}}, "use_361": {"+": {"?": ["R1Y99QL3NMW284"]}}, "use_362": {"+": {"perf_315": ["REPKJ0D222GL5"], "perf_318": ["REPKJ0D222GL5"]}}, "use_363": {"+": {"ATTR_333": ["R30AZ7C1LFHEG0"], "perf_316": ["R30AZ7C1LFHEG0"]}}, "use_364": {"+": {"?": ["R1C4N9RK269DKI"]}}, "use_365": {"+": {"perf_319": ["R3RWWVDPCDJ5ME"]}}, "use_366": {"+": {"ATTR_90": ["R2Q01DN7D98YHD"]}}, "use_367": {"+": {"perf_320": ["R21SOY8I7HIQT4"]}}, "use_368": {"+": {"?": ["R1P0E6L9A5EGC9"]}}, "use_369": {"-": {"perf_324": ["R3GTJYCVL4TYYL"]}}, "use_370": {"+": {"?": ["R3OX1TPUJDFBBI"]}}, "use_371": {"-": {"ATTR_337": ["R198SAS1EBGAZL"]}}, "use_372": {"+": {"perf_329": ["R72O9QR9P3IPY"], "?": ["R2QFXV0M2O9SL", "R1FTHSK8S6KAWN"]}}, "use_373": {"+": {"?": ["R3LXUBG8NKEN5Q"]}}, "use_374": {"+": {"?": ["RL10B0MEVWEGN"]}}, "use_375": {"-": {"ATTR_349": ["R3ECQBYLOE21O"]}}, "use_376": {"+": {"?": ["R2OVX3SN4UW322"]}}, "use_377": {"+": {"?": ["R10DGA7IAY9W4B"]}}, "use_378": {"-": {"ATTR_124": ["R2016F19YY3PM"]}}, "use_379": {"-": {"ATTR_124": ["R3N8LFP16E82HL"]}}, "use_380": {"+": {"?": ["R2WP0YPG2H9G4W"]}}, "use_381": {"-": {"perf_334": ["R38G0Y592QH460"]}}, "use_382": {"+": {"?": ["R2IEEK9OMGTZZG"]}}, "use_383": {"+": {"ATTR_356": ["R1MFZTHBOZ3YW3"], "?": ["R3SK22SLJQM29T"]}}, "use_384": {"+": {"ATTR_357": ["R3EOFKWJZBYH4U"]}}, "use_385": {"+": {"ATTR_358": ["R1J1GW8WBQAA8V"]}}, "use_386": {"+": {"?": ["R3KWT984G5ISWF"]}}, "use_387": {"+": {"perf_345": ["R2U9BCN1XIQDNQ"]}}, "use_388": {"+": {"perf_349": ["R1DWP6R1HLW4GH"]}}, "use_389": {"+": {"perf_349": ["R3GGBSY33TC262"]}}, "use_390": {"+": {"?": ["R3SRKZUWXCGEQE"]}}, "use_391": {"+": {"perf_349": ["RMVRLEBB1FGXK"]}}, "use_392": {"-": {"ATTR_360": ["RQ6HUH92KXDPU"]}}, "use_393": {"+": {"ATTR_233": ["R2KWYEECSY0CFO"]}}, "use_394": {"+": {"perf_354": ["R1XG04P6NK8IYG"]}}, "use_395": {"+": {"?": ["R2D91W1UUUSBF7"]}}, "use_396": {"+": {"perf_356": ["R1LB9R09RBJ34T"]}}, "use_397": {"+": {"ATTR_373": ["R2U4LBN9U9AUA5"]}}, "use_398": {"+": {"?": ["RTJRGOKRIQ8WL"]}}, "use_399": {"+": {"ATTR_49": ["RTJRGOKRIQ8WL"]}}, "use_400": {"+": {"?": ["RJJAGOKLQTT4F"]}}, "use_401": {"+": {"ATTR_374": ["R1PJT2X57EYCT4"]}}, "use_402": {"+": {"perf_4": ["R1LK6GCAAIPP0W"]}}, "use_403": {"+": {"?": ["R2P4OKWPRAHU9R"]}}, "use_404": {"+": {"ATTR_371": ["R2G0SVQU1F5XJ6"]}}, "use_405": {"+": {"perf_4": ["R7NJC9EJHM4A7"]}}, "use_406": {"+": {"perf_358": ["R260B14WCYSUKA"]}}, "use_407": {"+": {"ATTR_368": ["RVAUGD7R18V4O", "RFEQ915ZOXO7W"]}}, "use_408": {"+": {"?": ["R3EEDTH39FFOAL"]}}, "use_409": {"-": {"perf_357": ["R2ULA2HZB7Y33K"]}}, "use_410": {"+": {"?": ["R3NV4BB0RFSZR3"]}}, "use_411": {"+": {"ATTR_369": ["RX0S0O2Z2DNF"]}}, "use_412": {"+": {"ATTR_368": ["RYA6XC57YSHUW"]}}, "use_413": {"+": {"perf_359": ["R15XNQXBMM543K"]}}, "use_414": {"+": {"perf_57": ["R1KBLPEZXQCR75"]}}, "use_415": {"+": {"perf_57": ["RGCPEOWKOQ10F"]}}, "use_416": {"+": {"perf_57": ["RJ0VD8E70C7IZ"]}}, "use_417": {"+": {"perf_359": ["RZAHYWLL51NNL"]}}, "use_418": {"-": {"ATTR_23": ["R2UOMUSLK0KDFD"]}}, "use_419": {"+": {"perf_363": ["R2IQ89OYC3YSO2"], "perf_364": ["R2IQ89OYC3YSO2"]}}, "use_420": {"+": {"ATTR_381": ["R25MBUIB74EN6T"]}}, "use_421": {"+": {"perf_32": ["R383FAQWC39E4", "R2WZKD9NY4J5WM"]}}, "use_422": {"+": {"?": ["R3M1O6QG2V00AR"]}}, "use_423": {"+": {"perf_32": ["R3MJALZGPO4WWO"], "perf_370": ["R3MJALZGPO4WWO"], "perf_371": ["R3MJALZGPO4WWO"], "perf_372": ["R3MJALZGPO4WWO"]}}, "use_424": {"+": {"perf_32": ["R3H2EO2Z9AE4TW"]}}, "use_425": {"+": {"perf_32": ["R3OFN5HBWVR64M"], "ATTR_177": ["R3OFN5HBWVR64M"]}}, "use_426": {"+": {"?": ["R3MN29K17VC0X1"]}}, "use_427": {"+": {"?": ["R3UQT1V0RL90MU"]}}, "use_428": {"+": {"perf_32": ["R35VRMKC3H37IW"], "perf_369": ["R35VRMKC3H37IW"]}}, "use_429": {"+": {"perf_374": ["R28Y55KHC5TXTW"]}}, "use_430": {"+": {"?": ["R1BK4GF4EN2RI5"]}}, "use_431": {"+": {"?": ["R2HW9QED7OR0YQ"]}}, "use_432": {"+": {"?": ["R31ZWVQNJMBYJ1"]}}, "use_433": {"+": {"perf_375": ["R14L3APPUXB19P"]}}, "use_434": {"+": {"?": ["R3NLCJDQULUH0K"]}}, "use_435": {"+": {"perf_376": ["RDRWON2M3EA4T"]}}, "use_436": {"+": {"perf_377": ["R8LNQ967HH9L8", "R1LZ57BN1KABM0", "R2ZGNRWZKYISDQ"]}}, "use_437": {"+": {"?": ["RHH8Y14NSDQWJ"]}}, "use_438": {"-": {"perf_378": ["RNPO2SRRMV0IX"]}}, "use_439": {"+": {"perf_379": ["R58T16RA32Y5M"]}}, "use_440": {"-": {"perf_380": ["RK0FSW0NPF57I"]}}, "use_441": {"+": {"?": ["R1U1RF7F03M2R8"]}}, "use_442": {"+": {"?": ["R283HVUASPTV95"]}}, "use_443": {"-": {"perf_382": ["R14UON11P8R4AM"]}}, "use_444": {"+": {"ATTR_392": ["R36IRC0I9VSOA7"]}}, "use_445": {"+": {"ATTR_398": ["RPKG66IC9IXA1"]}}, "use_446": {"+": {"?": ["RS7HNCG8G3QUE", "R1RUZN0NX6MEWY"]}}, "use_447": {"+": {"ATTR_393": ["R3LCF0IUY2MLDT"]}}, "use_448": {"+": {"?": ["R1WCOF6777T15H"]}}, "use_449": {"+": {"?": ["R30YL7VCYY3TA5"]}}, "use_450": {"+": {"ATTR_393": ["R26K7DX2AZ87R1"]}}, "use_451": {"+": {"?": ["R1HJBSWCZLQLNN"]}}, "use_452": {"+": {"ATTR_400": ["RN1L1SHIZLCJP", "R3DKLW05BZX7MO", "R3S0E7NA2XWPOG", "RC2JZ45JSAW6X", "R21EK9SB6S3YB2", "R2V61KF216YBV0", "RQ3YT2SL0BA5V"], "?": ["R2FNWE7LZJ1CIB", "R77114PSD0T7A"]}}, "use_453": {"+": {"ATTR_400": ["R2LPVRZKLI7GN5", "R3S0E7NA2XWPOG"]}}, "use_454": {"+": {"ATTR_403": ["R1PJRK1CZCYCRN"]}}, "use_455": {"+": {"ATTR_400": ["R1KZC4W7RJUBKC"], "perf_391": ["R1KZC4W7RJUBKC"]}}, "use_456": {"+": {"perf_390": ["R2Q2RXTKIJC5RK"]}}, "use_457": {"+": {"ATTR_400": ["R77114PSD0T7A"]}}, "use_458": {"+": {"ATTR_90": ["R21EK9SB6S3YB2"]}}, "use_459": {"+": {"ATTR_400": ["R2V61KF216YBV0", "RQ3YT2SL0BA5V"]}}, "use_460": {"+": {"perf_392": ["R3VFVC0GTOQJGL"]}}, "use_461": {"+": {"perf_392": ["R3ME9O2K9LCFHD"]}}, "use_462": {"+": {"perf_392": ["R1WPHV8P9Y4IL1"], "ATTR_156": ["R1WPHV8P9Y4IL1"]}}, "use_463": {"+": {"perf_392": ["R1VZOJ665EBJEM"]}}, "use_464": {"+": {"perf_393": ["RH3W0BWKVFE2W"]}}, "use_465": {"+": {"perf_392": ["RHE5H37QRYD65"]}}, "use_466": {"+": {"perf_392": ["RIHDVHLO6GL7I"], "perf_394": ["RIHDVHLO6GL7I"]}}, "use_467": {"+": {"perf_392": ["R2K3P7LNNO98H9"]}}, "use_468": {"-": {"perf_392": ["R3JWKONN4H4QU6"]}}, "use_469": {"+": {"perf_395": ["R1CV7NZ953Y0MW"]}}, "use_470": {"+": {"ATTR_156": ["R7UDPOLBFRX03"]}}, "use_471": {"+": {"?": ["R3E372HSHL7MJ4", "R21633J60AM6MG", "R2AZDS6BK455P2", "ROAZL8J0IKLPJ", "R29ZMSNA882OEQ", "R3EPOBXLIQMXMY", "R1993QDE44B8P5", "R153M8CPIXRMI5", "R18FP0E5WL9OX2", "R1HTYU9YL0JYYP", "RME4G596O1UL5", "RZMPAJFJ8F6SP", "R1ETS09XCY8I93", "R3VVSP52HI3HXS", "RBMGAQBFMAOM5", "RZCR8NVY75LH", "R1JP8MGFO1QDZ", "R26SEU0QXNNAMV", "R2CKYCX4JWPX58", "R37C0N84ECVEFW", "R36HED9SSOGZ7U", "R2FXOX0UN68ZSY", "R3IEUQ4SFDLRYT", "R2KQWHHLCVG1IA", "RSUMH9CNGXM43", "R1V9YMI5QUNRUJ", "R782NCLGTI108", "R2TXRSY3RXHEUJ", "R96ZJXY59FW95"]}}, "use_472": {"+": {"?": ["R2J5XL8L5ZPMOL"]}}, "use_473": {"+": {"perf_4": ["R33IHEQPO4ZHR8"]}}, "use_474": {"+": {"perf_4": ["R1XWDC1MCY7UQP"], "perf_401": ["R1XWDC1MCY7UQP"]}}, "use_475": {"+": {"?": ["RUWU735G1FVNA"]}}, "use_476": {"+": {"?": ["R1JZWBWIW0LI0I"]}}, "use_477": {"+": {"?": ["R416OUP6V2CQE"]}}, "use_478": {"+": {"perf_4": ["R28AI9CWQ9XO8K"]}}, "use_479": {"+": {"ATTR_411": ["R18O0LIP2F58BF"], "ATTR_412": ["R18O0LIP2F58BF"], "ATTR_413": ["R18O0LIP2F58BF"]}}, "use_480": {"-": {"perf_398": ["R2NTU7OGY225F0"]}}, "use_481": {"+": {"perf_405": ["R155OGJ1EMT4J4"], "ATTR_156": ["R155OGJ1EMT4J4"]}}, "use_482": {"+": {"perf_408": ["R1PSKFQ2J61EW"]}}, "use_483": {"+": {"perf_411": ["R27P9KO4H8DHIF"]}}, "use_484": {"-": {"ATTR_416": ["R3HAHL5RDL25TW"]}}, "use_485": {"+": {"?": ["R1W3T0CTY26AJJ"]}}, "use_486": {"+": {"perf_413": ["R1QC2DI64W95L8"], "ATTR_416": ["R1QC2DI64W95L8"], "ATTR_157": ["R1QC2DI64W95L8"], "ATTR_418": ["R1QC2DI64W95L8"]}}, "use_487": {"+": {"perf_408": ["RJH91JRTRMZAI"], "perf_414": ["RJH91JRTRMZAI"]}}, "use_488": {"+": {"?": ["R2C320AA61BXGE"]}}, "use_489": {"+": {"perf_413": ["R33J9YIT2F62KE"], "perf_415": ["R33J9YIT2F62KE"]}}, "use_490": {"+": {"ATTR_417": ["R20HQYAQUBBTAJ"], "ATTR_157": ["R20HQYAQUBBTAJ"], "ATTR_158": ["R20HQYAQUBBTAJ"]}}, "use_491": {"+": {"?": ["R1U5T4EVGPD8LV"]}}, "use_492": {"+": {"ATTR_416": ["R1A3JCGF57ST0E"], "perf_407": ["R1A3JCGF57ST0E"], "perf_405": ["R1A3JCGF57ST0E"]}}, "use_493": {"+": {"?": ["R24LZL4F8DXKBE"]}}, "use_494": {"+": {"perf_408": ["R2TIF5UYLOEQBE"]}}, "use_495": {"-": {"perf_94": ["R1BN7PT696C6DL", "R3S9EIXESMPQVE", "R2ESH8M5CZJJO4"], "?": ["R7PYEMTEQXFWS"]}, "+": {"perf_416": ["R9F2JH9RSPNDL"]}}, "use_496": {"+": {"?": ["R1NF1H1UW69GV3"]}}, "use_497": {"+": {"?": ["R339QK8N9JH8L3"]}}, "use_498": {"+": {"ATTR_281": ["R1DXOFMZCAY0MZ"]}}, "use_499": {"+": {"ATTR_419": ["R2LJXYHCSV7DCP"]}}, "use_500": {"-": {"perf_238": ["R3HH44CUKMQW75"], "ATTR_424": ["R3HH44CUKMQW75"]}}, "use_501": {"-": {"perf_238": ["R1716H5VBXJBHE"], "ATTR_424": ["R1716H5VBXJBHE"]}}, "use_502": {"+": {"ATTR_424": ["RLLFYZ0V3U306"]}}, "use_503": {"-": {"perf_422": ["R17WQLYHQ066XN"]}}, "use_504": {"+": {"ATTR_424": ["R17WQLYHQ066XN"]}}, "use_505": {"-": {"perf_421": ["R1U5M9NQHH49S2"], "ATTR_428": ["R1U5M9NQHH49S2"]}}, "use_506": {"-": {"perf_420": ["R2XR9WF8POKBF7"], "ATTR_424": ["R2XR9WF8POKBF7"]}}, "use_507": {"+": {"ATTR_424": ["RNIOVFO8SDZD5"]}}, "use_508": {"-": {"perf_420": ["R32SV8NHD02K3H"], "ATTR_424": ["R32SV8NHD02K3H"], "ATTR_426": ["R32SV8NHD02K3H"]}}, "use_509": {"+": {"?": ["R1AZGXRHP7Q5XY"]}}, "use_510": {"+": {"?": ["R3K7Y9A9ZB65VJ"]}}, "use_511": {"-": {"ATTR_429": ["R3AB1O5COW49WW"]}}, "use_512": {"+": {"?": ["RU1Z36SYF7BZY"]}}, "use_513": {"-": {"?": ["R1F7GTB3A7YEH7"]}}, "use_514": {"-": {"ATTR_432": ["RNW7NL5G236VA"]}}, "use_515": {"+": {"?": ["R2U4B7WKDM8B3E"]}}, "use_516": {"+": {"?": ["R2YKQDNHH6F04I"]}}, "use_517": {"+": {"?": ["RJPLK6FFPAQFM"]}}, "use_518": {"-": {"?": ["R1JEJCYO37941I"]}}, "use_519": {"+": {"?": ["R24149JN3V8GXF"]}}, "use_520": {"+": {"?": ["R1CVKQDAN402JH"]}}, "use_521": {"+": {"perf_433": ["R1G3R83ZSET52M"]}}, "use_522": {"+": {"perf_433": ["R1G3R83ZSET52M"]}}, "use_523": {"+": {"perf_433": ["R9744ODG830NY"], "perf_440": ["R9744ODG830NY"]}}, "use_524": {"+": {"perf_433": ["RDN0XFMGDG5MF"], "ATTR_49": ["R3K9WX4RVXZK9L"]}}, "use_525": {"+": {"ATTR_49": ["R3K9WX4RVXZK9L"]}}, "use_526": {"+": {"perf_442": ["R2R65OA1231VL7", "RIYH8K00CXRXE", "R29GRGXV20VLRN", "R2EN49V6IO8GGW", "R2TWNWPOB2Y2E6", "R1T4P6BJTXI6I9"], "?": ["R2DQCN74VJDE7A", "R1UURWV1R9B7UA"]}}, "use_527": {"+": {"ATTR_157": ["R35RV15JEOCSTD"]}}, "use_528": {"+": {"?": ["R2RSSLIHUARD10"]}}, "use_529": {"+": {"perf_442": ["R1EHX08AX54ZMX"]}}, "use_530": {"+": {"?": ["R2CYSRGCVZY3W2"]}}, "use_531": {"+": {"?": ["R2CYSRGCVZY3W2"]}}, "use_532": {"+": {"?": ["R1DUINZ85ZJEM2"]}}, "use_533": {"-": {"perf_449": ["R3QA8VDE7WG91H"], "ATTR_451": ["R3QA8VDE7WG91H"]}}, "use_534": {"-": {"perf_94": ["RKFXKXPI3TDUM"]}}, "use_535": {"-": {"ATTR_430": ["R1NTHQLULLNBH2"], "perf_451": ["R1NTHQLULLNBH2"]}}, "use_536": {"+": {"perf_446": ["RYLAQVB99RMIQ"]}}, "use_537": {"+": {"ATTR_449": ["R2OV43ULK3CEJ"], "perf_454": ["R2OV43ULK3CEJ"]}}, "use_538": {"+": {"?": ["R39ZBPYX0J8XV4"]}}, "use_539": {"-": {"perf_457": ["RHJOLX2B9WF1C"]}}, "use_540": {"-": {"perf_455": ["R3DYEC6WGWUFZH"]}}, "use_541": {"-": {"perf_455": ["R3NGZOAV4O0G9J"]}}, "use_542": {"+": {"perf_3": ["RCHCE1YBX6S60"], "perf_461": ["RCHCE1YBX6S60"], "perf_462": ["RCHCE1YBX6S60"]}}, "use_543": {"+": {"?": ["RCHCE1YBX6S60"]}}, "use_544": {"-": {"perf_458": ["RCHCE1YBX6S60"]}}, "use_545": {"-": {"perf_456": ["RPOWL4NDFZOYV"]}}, "use_546": {"-": {"ATTR_457": ["R3N4613SFPAVPK"]}}, "use_547": {"+": {"ATTR_457": ["R3N4613SFPAVPK"]}}, "use_548": {"-": {"ATTR_458": ["R9F1RB29VF13L"], "ATTR_459": ["R9F1RB29VF13L"]}}, "use_549": {"+": {"?": ["RTRGAH17OTYJD"]}}, "use_550": {"-": {"perf_459": ["RTRGAH17OTYJD"]}}, "use_551": {"-": {"perf_455": ["R27V09I3NBROB8"], "ATTR_456": ["R27V09I3NBROB8"]}}, "use_552": {"+": {"ATTR_464": ["R1DSG7AM0SFB6F"]}}, "use_553": {"+": {"ATTR_461": ["R160XQSSKNNUP4"], "ATTR_464": ["R160XQSSKNNUP4"], "ATTR_465": ["R160XQSSKNNUP4"], "ATTR_271": ["R160XQSSKNNUP4"], "ATTR_468": ["R160XQSSKNNUP4"]}}, "use_554": {"+": {"?": ["R28R1UVVZDRHIU"]}}, "use_555": {"-": {"perf_467": ["R2T9H7FRS4CR00"]}}, "use_556": {"+": {"?": ["R1EW4P092XZS1S"]}}, "use_557": {"+": {"?": ["R3C89M50UB2JTO"]}}, "use_558": {"-": {"ATTR_15": ["R34AW7U3HMNW6A"], "ATTR_405": ["R34AW7U3HMNW6A"]}}, "use_559": {"+": {"perf_476": ["RMPUY4D973ZPX", "R17OX7UNNRZQL", "R14ET2NYRO9ICA", "R3RVD5P2KU9222", "RHKMUJDZP1FZB"]}}, "use_560": {"+": {"perf_476": ["R2H0R809USX6L7", "RMPUY4D973ZPX"]}}, "use_561": {"+": {"perf_482": ["R1JCG4WAD13NUG"]}}, "use_562": {"+": {"perf_485": ["R16D28MW5P7DM0"]}}, "use_563": {"+": {"perf_477": ["RGSV7JIXA3ZOJ", "RLR6ZJGTWW474", "R3Q2GQJICKAJDF"]}}, "use_564": {"-": {"ATTR_475": ["R3TSXIWAQUFE"]}}, "use_565": {"+": {"?": ["R1WTCPX8ORPPOD"]}}, "use_566": {"+": {"perf_486": ["RP4C3KGO0Z9XT"]}}, "use_567": {"+": {"perf_487": ["RHKMUJDZP1FZB"]}}, "use_568": {"+": {"?": ["R1D6ZIIM7QYB49"]}}, "use_569": {"+": {"?": ["R1ZO8GWHQVD50U"]}}, "use_570": {"+": {"perf_490": ["R3TI0PW2VHUWED"]}}, "use_571": {"+": {"?": ["R1UOZGTRCQFM3R", "R265SO8YZH86M7"]}}, "use_572": {"+": {"perf_32": ["R1GSEKEWO18DA", "R1MAY5GC4IQZ0C", "R3RY5N1HS9ZGCU", "RWTB16YNYU8DL", "R1J9CD4MRXYP6R", "R156GLPJ71YI4Y", "R2U8UJ2W463V0J", "RAT3D9CZ5Q8W4"], "?": ["R30GKFGDN5PHPI", "RF1UQLITZZRBB"]}, "-": {"perf_361": ["RG07VUZR9FS5W"], "perf_471": ["R39SC1IAP8TWVQ"]}}, "use_573": {"+": {"perf_32": ["R200I3WG72IYOW"]}}, "use_574": {"+": {"perf_32": ["RPPQSB22QY5C8"], "?": ["R30GKFGDN5PHPI"]}}, "use_575": {"+": {"perf_32": ["RANLJWI60P5XB"]}}, "use_576": {"+": {"perf_32": ["RQJ9R392EM87Z"], "perf_500": ["RQJ9R392EM87Z"]}}, "use_577": {"+": {"perf_32": ["RQJ9R392EM87Z"], "perf_500": ["RQJ9R392EM87Z"]}}, "use_578": {"+": {"ATTR_90": ["RQJ9R392EM87Z", "RD3X23YQTXRS2"]}}, "use_579": {"+": {"perf_500": ["RQJ9R392EM87Z"]}}, "use_580": {"+": {"ATTR_90": ["RD3X23YQTXRS2"], "perf_32": ["RD3X23YQTXRS2"]}}, "use_581": {"-": {"perf_498": ["R3HDXNO1XR4FEG"]}}, "use_582": {"-": {"perf_501": ["R3HDXNO1XR4FEG"]}}, "use_583": {"-": {"perf_499": ["R1H4F54S5ZCRIH"], "perf_502": ["R1H4F54S5ZCRIH"]}}, "use_584": {"+": {"perf_503": ["R1H2HSTFNME1GB"]}}, "use_585": {"+": {"?": ["R1I0GETDCYZVZ3"]}}, "use_586": {"+": {"?": ["R2F1HW911OQKGQ"]}}, "use_587": {"-": {"?": ["RZHTBARNACIH1"]}}, "use_588": {"+": {"?": ["R99JQC59JUOY3"]}}, "use_589": {"+": {"?": ["R10T1M5KPZUD8A"]}}, "use_590": {"+": {"?": ["R10T1M5KPZUD8A"]}}, "use_591": {"+": {"?": ["RP9YBUYJ5G9XH"]}}, "use_592": {"+": {"?": ["R1S0M48BU81WOO"]}}, "use_593": {"+": {"?": ["RFZEW3ES6E38A"]}}, "use_594": {"+": {"ATTR_239": ["R1P16SIK7JGA3E"]}}, "use_595": {"+": {"perf_170": ["RBOS3XCWMPSN3"]}}, "use_596": {"+": {"?": ["R1Z6TXX5AJ7H6V"]}}, "use_597": {"+": {"?": ["R3PCSBMF11N2TD"]}}, "use_598": {"+": {"ATTR_34": ["RVVP3OFPUMW49"]}}, "use_599": {"-": {"perf_513": ["R1IRVT2ZZ2KFSJ"]}}, "use_600": {"-": {"ATTR_23": ["R2FZDC6ZPEE9P2"]}}, "use_601": {"-": {"perf_519": ["R17BOKI80S9IVK"]}}, "use_602": {"-": {"ATTR_23": ["R33UETIO7ZU0GD"]}}, "use_603": {"-": {"ATTR_23": ["R1PM9YT17BVVWV"]}}, "use_604": {"-": {"ATTR_23": ["R22G7I8YW7ILK5"], "perf_517": ["R22G7I8YW7ILK5"]}}, "use_605": {"-": {"perf_513": ["R22G7I8YW7ILK5"]}}, "use_606": {"-": {"perf_512": ["RAIAAEGGKPMZA"]}}, "use_607": {"+": {"?": ["RZLWQB78VHPKX"]}}, "use_608": {"-": {"ATTR_23": ["R390AOLCCDPR8L"], "perf_515": ["R390AOLCCDPR8L"]}}, "use_609": {"+": {"?": ["RROZPICBCXQPH"]}}}